sqlclasses/__init__.py
sqlclasses/sql.py
sqlclasses-1.4.dist-info/LICENSE
sqlclasses-1.4.dist-info/METADATA
sqlclasses-1.4.dist-info/WHEEL
sqlclasses-1.4.dist-info/top_level.txt
sqlclasses-1.4.dist-info/RECORD
