Metadata-Version: 2.2
Name: sqlclasses
Version: 1.4
Summary: Construct SQL commands and queries using Python classes.
Home-page: https://github.com/dvorberg/sqlclasses
Author: Diedrich Vorberg
Author-email: diedrich@tux4web.de
Classifier: Programming Language :: Python :: 3
Classifier: License :: OSI Approved :: GNU General Public License v3 (GPLv3)
Classifier: Operating System :: OS Independent
Requires-Python: >=3.7
License-File: LICENSE
Dynamic: author
Dynamic: author-email
Dynamic: classifier
Dynamic: description
Dynamic: description-content-type
Dynamic: home-page
Dynamic: requires-python
Dynamic: summary
